cssselect/__init__.py
cssselect/parser.py
cssselect/xpath.py
cssselect-1.0.0.dist-info/DESCRIPTION.rst
cssselect-1.0.0.dist-info/METADATA
cssselect-1.0.0.dist-info/RECORD
cssselect-1.0.0.dist-info/WHEEL
cssselect-1.0.0.dist-info/metadata.json
cssselect-1.0.0.dist-info/top_level.txt
