Metadata-Version: 1.1
Name: cssselect
Version: 1.0.0
Summary: cssselect parses CSS3 Selectors and translates them to XPath 1.0
Home-page: https://pythonhosted.org/cssselect/
Author: Paul Tremberth
Author-email: paul.tremberth@gmail.com
License: BSD
Platform: UNKNOWN
Classifier: Development Status :: 4 - Beta
Classifier: Intended Audience :: Developers
Classifier: License :: OSI Approved :: BSD License
Classifier: Programming Language :: Python :: 2
Classifier: Programming Language :: Python :: 2.6
Classifier: Programming Language :: Python :: 2.7
Classifier: Programming Language :: Python :: 3
Classifier: Programming Language :: Python :: 3.2
Classifier: Programming Language :: Python :: 3.3
Classifier: Programming Language :: Python :: 3.4
Classifier: Programming Language :: Python :: 3.5
